sickulator/__init__.py
sickulator/agent.py
sickulator/buildings.py
sickulator/game.py
sickulator/grid.py
sickulator/main.py
sickulator/menus.py
sickulator/path_finder.py
sickulator/settings.py
sickulator/simulation.py
sickulator/sprites.py
sickulator/theme.json
sickulator/tiles.py
sickulator/agent_sprites/healthyglob.png
sickulator/agent_sprites/healthyglob_selected.png
sickulator/agent_sprites/immuneglob.png
sickulator/agent_sprites/immuneglob_selected.png
sickulator/agent_sprites/sickglob.png
sickulator/agent_sprites/sickglob_infected.png
sickulator/agent_sprites/sickglob_selected.png
sickulator/data/data.txt
sickulator/data/temp_results.png
sickulator/map/agentcity.tmx
sickulator/map/agentcityO.tmx
sickulator/map/map.tmx
sickulator/map/path_Map.tmx
sickulator/map/path_MapO.tmx
sickulator/map/roguelikeCity_magenta.png
sickulator/map/roguelikeCity_magenta.tsx
sickulator-2.0.1.dist-info/METADATA
sickulator-2.0.1.dist-info/WHEEL
sickulator-2.0.1.dist-info/entry_points.txt
sickulator-2.0.1.dist-info/top_level.txt
sickulator-2.0.1.dist-info/RECORD
