Metadata-Version: 2.1
Name: sickulator
Version: 2.0.1
Summary: Pandemic Simulator
Home-page: https://github.com/JKornberg/Sickulator/
License: UNKNOWN
Platform: UNKNOWN
Requires-Python: <4,>=3.8
Requires-Dist: numpy (>=1.20.3)
Requires-Dist: pygame (>=2.0.1)
Requires-Dist: pygame-gui (>=0.5.7)
Requires-Dist: pygame-menu (>=4.1.1)
Requires-Dist: PyTMX (>=3.25)
Requires-Dist: seaborn (>=0.11.1)
Requires-Dist: names (>=0.3.0)
